customhys/__init__.py
customhys/benchmark_func.py
customhys/characterisation.py
customhys/experiment.py
customhys/hyperheuristic.py
customhys/machine_learning.py
customhys/metaheuristic.py
customhys/operators.py
customhys/population.py
customhys/test_solvers.py
customhys/tools.py
customhys/visualisation.py
customhys/collections/automatic.txt
customhys/collections/basicmetaheuristics.txt
customhys/collections/default.txt
customhys/collections/operators_collection.txt
customhys/collections/operators_weights.json
customhys/collections/short_collection.txt
customhys/exconf/basic_metaheuristic.json
customhys/exconf/brute_force.json
customhys/exconf/demo.json
customhys/exconf/demo_neural_network.json
customhys/exconf/long1.json
customhys/exconf/short1.json
customhys/exconf/short2.json
customhys-1.1.0.dist-info/LICENSE
customhys-1.1.0.dist-info/METADATA
customhys-1.1.0.dist-info/WHEEL
customhys-1.1.0.dist-info/top_level.txt
customhys-1.1.0.dist-info/RECORD
